dsdfe/__init__.py
dsdfe/extract.py
dsdfe/transform.py
dsdfe/utils.py
dsdfe-0.0.1.dist-info/LICENSE
dsdfe-0.0.1.dist-info/METADATA
dsdfe-0.0.1.dist-info/WHEEL
dsdfe-0.0.1.dist-info/top_level.txt
dsdfe-0.0.1.dist-info/RECORD
